plom/aliceBob.py
plom/comment_utils.py
plom/common.py
plom/demo_rubrics.toml
plom/feedback_rules.py
plom/idBox2.pdf
plom/idBox4.pdf
plom/latexTemplate.tex
plom/latexTemplatev2.tex
plom/manage_user_files.py
plom/misc_utils.py
plom/plom_exceptions.py
plom/question_labels.py
plom/rubric_utils.py
plom/rules.py
plom/spec_verifier.py
plom/tagging.py
plom/templateSolutionSpec.toml
plom/templateTestSpec.toml
plom/templateUserList.csv
plom/test_exceptions.py
plom/test_feedback_rules.py
plom/test_illadvised.py
plom/test_latex.py
plom/test_latexfrag.py
plom/test_misc_utils.py
plom/test_print_score.py
plom/test_question_labels.py
plom/test_rubric_diff.py
plom/test_scoring.py
plom/test_spec.py
plom/test_tags.py
plom/test_target_latex.png
plom/test_target_latex_old.png
plom/test_version.py
plom/test_version_maps.py
plom/textools.py
plom/tpv_utils.py
plom/version_maps.py
plom/canvas/__init__.py
plom/canvas/canvas_utils.py
plom/canvas/canvasapi_extensions.py
plom/cli/__init__.py
plom/cli/__main__.py
plom/cli/bundle_tools.py
plom/cli/classlist_tools.py
plom/cli/finish_tools.py
plom/cli/identify_tools.py
plom/cli/list_bundles.py
plom/cli/papers.py
plom/cli/pqvmap_tools.py
plom/cli/rectangle_extractor_tools.py
plom/cli/source_tools.py
plom/cli/spec_tools.py
plom/cli/start_messenger.py
plom/cli/task_tools.py
plom/create/__init__.py
plom/create/__main__.py
plom/create/_digitHunter.py
plom/create/buildClasslist.py
plom/create/build_bundle_separators_with_qrcodes.py
plom/create/build_extra_page_with_qrcodes.py
plom/create/build_scrap_paper_with_qrcodes.py
plom/create/bundle_separator_src.tex
plom/create/classlistValidator.py
plom/create/demotools.py
plom/create/digits.json
plom/create/exam_scribbler.py
plom/create/extra_pages_src.tex
plom/create/homework_scribbler.py
plom/create/mergeAndCodePages.py
plom/create/push_pull_rubrics.py
plom/create/scrap_paper_src.tex
plom/create/scribble_hw_utils.py
plom/create/scribble_utils.py
plom/create/start_messenger.py
plom/create/status.py
plom-0.20.0.dist-info/licenses/LICENSE.md
plom-0.20.0.dist-info/METADATA
plom-0.20.0.dist-info/WHEEL
plom-0.20.0.dist-info/entry_points.txt
plom-0.20.0.dist-info/top_level.txt
plom-0.20.0.dist-info/RECORD
